aliyunsdkdcdn/__init__.py
aliyunsdkdcdn/endpoint.py
aliyunsdkdcdn/request/__init__.py
aliyunsdkdcdn/request/v20180115/AddDcdnDomainRequest.py
aliyunsdkdcdn/request/v20180115/AddDcdnIpaDomainRequest.py
aliyunsdkdcdn/request/v20180115/BatchAddDcdnDomainRequest.py
aliyunsdkdcdn/request/v20180115/BatchCreateDcdnWafRulesRequest.py
aliyunsdkdcdn/request/v20180115/BatchDeleteDcdnDomainConfigsRequest.py
aliyunsdkdcdn/request/v20180115/BatchDeleteDcdnKvRequest.py
aliyunsdkdcdn/request/v20180115/BatchDeleteDcdnKvWithHighCapacityRequest.py
aliyunsdkdcdn/request/v20180115/BatchDeleteDcdnWafRulesRequest.py
aliyunsdkdcdn/request/v20180115/BatchModifyDcdnWafRulesRequest.py
aliyunsdkdcdn/request/v20180115/BatchPutDcdnKvRequest.py
aliyunsdkdcdn/request/v20180115/BatchPutDcdnKvWithHighCapacityRequest.py
aliyunsdkdcdn/request/v20180115/BatchSetDcdnDomainCertificateRequest.py
aliyunsdkdcdn/request/v20180115/BatchSetDcdnDomainConfigsRequest.py
aliyunsdkdcdn/request/v20180115/BatchSetDcdnIpaDomainConfigsRequest.py
aliyunsdkdcdn/request/v20180115/BatchSetDcdnWafDomainConfigsRequest.py
aliyunsdkdcdn/request/v20180115/BatchStartDcdnDomainRequest.py
aliyunsdkdcdn/request/v20180115/BatchStopDcdnDomainRequest.py
aliyunsdkdcdn/request/v20180115/CheckDcdnProjectExistRequest.py
aliyunsdkdcdn/request/v20180115/CommitStagingRoutineCodeRequest.py
aliyunsdkdcdn/request/v20180115/CreateDcdnCertificateSigningRequestRequest.py
aliyunsdkdcdn/request/v20180115/CreateDcdnDeliverTaskRequest.py
aliyunsdkdcdn/request/v20180115/CreateDcdnSLSRealTimeLogDeliveryRequest.py
aliyunsdkdcdn/request/v20180115/CreateDcdnSubTaskRequest.py
aliyunsdkdcdn/request/v20180115/CreateDcdnWafGroupRequest.py
aliyunsdkdcdn/request/v20180115/CreateDcdnWafPolicyRequest.py
aliyunsdkdcdn/request/v20180115/CreateRoutineRequest.py
aliyunsdkdcdn/request/v20180115/CreateSlrAndSlsProjectRequest.py
aliyunsdkdcdn/request/v20180115/DeleteDcdnDeliverTaskRequest.py
aliyunsdkdcdn/request/v20180115/DeleteDcdnDomainRequest.py
aliyun_python_sdk_dcdn-2.2.19.dist-info/LICENSE
aliyun_python_sdk_dcdn-2.2.19.dist-info/METADATA
aliyun_python_sdk_dcdn-2.2.19.dist-info/WHEEL
aliyun_python_sdk_dcdn-2.2.19.dist-info/top_level.txt
aliyun_python_sdk_dcdn-2.2.19.dist-info/RECORD
